{
  "profiles": [
    {
      "bankKey": "ABANCA",
      "bankVersion": "2025.01.15",
      "headerAliases": {
        "date": ["fecha", "fecha operacion", "fecha operación", "f. operacion", "f. operación", "fecha mov", "fecha movimiento"],
        "valueDate": ["fecha valor", "fecha de valor", "f. valor", "f valor"],
        "amount": ["importe", "importe (€)", "importe eur", "cantidad", "monto", "euros"],
        "cargo": ["cargo", "cargos", "debito", "débito"],
        "abono": ["abono", "abonos", "credito", "crédito"],
        "description": ["concepto", "descripcion", "descripción", "detalle", "descripcion ampliada", "observaciones"],
        "counterparty": ["contraparte", "beneficiario", "ordenante", "entidad"],
        "balance": ["saldo", "saldo disponible", "saldo actual", "saldo tras"],
        "currency": ["divisa", "moneda", "currency"],
        "reference": ["referencia", "ref", "numero operacion", "número operación"]
      },
      "noisePatterns": [
        "saldo inicial", "saldo final", "saldo anterior", "saldo actual", 
        "subtotal", "total", "totales", "página", "page", "extracto", 
        "periodo", "desde", "hasta", "nº de cuenta", "iban", "titular", "oficina"
      ],
      "numberFormat": {
        "decimal": ",",
        "thousand": "."
      },
      "dateHints": ["dd/mm/yyyy", "dd-mm-yyyy"],
      "minScore": 3,
      "useCargoAbono": true
    },
    {
      "bankKey": "BBVA",
      "bankVersion": "2025.01.15", 
      "headerAliases": {
        "date": ["fecha", "fecha operacion", "fecha operación", "f. operacion", "f. operación", "fecha mov"],
        "valueDate": ["fecha valor", "fecha de valor", "f. valor", "f valor"],
        "amount": ["importe", "importe (€)", "importe eur", "cantidad", "monto", "euros"],
        "cargo": ["cargo", "cargos", "debito", "débito"],
        "abono": ["abono", "abonos", "credito", "crédito"],
        "description": ["concepto", "descripcion", "descripción", "detalle", "movimiento"],
        "counterparty": ["contraparte", "beneficiario", "ordenante"],
        "balance": ["saldo", "saldo disponible", "saldo actual", "saldo tras"],
        "currency": ["divisa", "moneda", "currency"],
        "reference": ["referencia", "ref", "numero operacion", "número operación"]
      },
      "noisePatterns": [
        "saldo inicial", "saldo final", "saldo anterior", "saldo actual", 
        "subtotal", "total", "totales", "página", "page", "extracto", 
        "periodo", "desde", "hasta", "nº de cuenta", "iban", "titular", "oficina"
      ],
      "numberFormat": {
        "decimal": ",",
        "thousand": "."
      },
      "dateHints": ["dd/mm/yyyy", "dd-mm-yyyy"],
      "minScore": 3,
      "useCargoAbono": true
    },
    {
      "bankKey": "Santander",
      "bankVersion": "2025.01.15",
      "headerAliases": {
        "date": ["fecha", "fecha operacion", "fecha operación", "f. operacion", "f. operación", "fecha mov"],
        "valueDate": ["fecha valor", "fecha de valor", "f. valor"],
        "amount": ["importe", "importe eur", "importe (€)", "cantidad", "monto", "euros"],
        "cargo": ["cargo", "cargos", "debito", "débito"],
        "abono": ["abono", "abonos", "credito", "crédito"],
        "description": ["concepto", "descripcion", "descripción", "detalle", "movimiento"],
        "counterparty": ["contraparte", "beneficiario", "ordenante"],
        "balance": ["saldo", "saldo disponible", "saldo actual", "saldo tras"],
        "currency": ["divisa", "moneda", "currency"],
        "reference": ["referencia", "ref", "numero operacion", "número operación"]
      },
      "noisePatterns": [
        "saldo inicial", "saldo final", "saldo anterior", "saldo actual", 
        "subtotal", "total", "totales", "página", "page", "extracto", 
        "periodo", "desde", "hasta", "nº de cuenta", "iban", "titular", "oficina"
      ],
      "numberFormat": {
        "decimal": ",",
        "thousand": "."
      },
      "dateHints": ["dd/mm/yyyy", "dd-mm-yyyy"],
      "minScore": 3,
      "useCargoAbono": true
    },
    {
      "bankKey": "Unicaja",
      "bankVersion": "2025.01.15",
      "headerAliases": {
        "date": ["fecha", "fecha operacion", "fecha operación", "f. operacion", "f. operación", "fecha mov"],
        "valueDate": ["fecha valor", "fecha de valor", "f. valor"],
        "amount": ["importe", "importe (€)", "cantidad", "monto", "euros"],
        "cargo": ["cargo", "cargos", "debito", "débito"],
        "abono": ["abono", "abonos", "credito", "crédito"],
        "description": ["concepto", "descripcion", "descripción", "detalle"],
        "counterparty": ["contraparte", "beneficiario", "ordenante"],
        "balance": ["saldo", "saldo disponible", "saldo actual"],
        "currency": ["divisa", "moneda", "currency"],
        "reference": ["referencia", "ref", "numero operacion", "número operación"]
      },
      "noisePatterns": [
        "saldo inicial", "saldo final", "saldo anterior", "saldo actual", 
        "subtotal", "total", "totales", "página", "page", "extracto", 
        "periodo", "desde", "hasta", "nº de cuenta", "iban", "titular", "oficina"
      ],
      "numberFormat": {
        "decimal": ",",
        "thousand": "."
      },
      "dateHints": ["dd/mm/yyyy", "dd-mm-yyyy"],
      "minScore": 3,
      "useCargoAbono": true
    },
    {
      "bankKey": "Sabadell",
      "bankVersion": "2025.01.15",
      "headerAliases": {
        "date": ["fecha", "fecha operacion", "fecha operación", "f. operacion", "f. operación", "fecha mov"],
        "valueDate": ["fecha valor", "fecha de valor", "f. valor"],
        "amount": ["importe", "importe (€)", "cantidad", "monto", "euros"],
        "cargo": ["cargo", "cargos", "debito", "débito"],
        "abono": ["abono", "abonos", "credito", "crédito"],
        "description": ["concepto", "descripcion", "descripción", "detalle"],
        "counterparty": ["contraparte", "beneficiario", "ordenante"],
        "balance": ["saldo", "saldo disponible", "saldo actual"],
        "currency": ["divisa", "moneda", "currency"],
        "reference": ["referencia", "ref", "numero operacion", "número operación"]
      },
      "noisePatterns": [
        "saldo inicial", "saldo final", "saldo anterior", "saldo actual", 
        "subtotal", "total", "totales", "página", "page", "extracto", 
        "periodo", "desde", "hasta", "nº de cuenta", "iban", "titular", "oficina"
      ],
      "numberFormat": {
        "decimal": ",",
        "thousand": "."
      },
      "dateHints": ["dd/mm/yyyy", "dd-mm-yyyy"],
      "minScore": 3,
      "useCargoAbono": true
    },
    {
      "bankKey": "Bankinter",
      "bankVersion": "2025.01.15",
      "headerAliases": {
        "date": ["fecha", "fecha operacion", "fecha operación", "f. operacion", "f. operación", "fecha mov"],
        "valueDate": ["fecha valor", "fecha de valor", "f. valor"],
        "amount": ["importe", "importe (€)", "cantidad", "monto", "euros"],
        "cargo": ["cargo", "cargos", "debito", "débito"],
        "abono": ["abono", "abonos", "credito", "crédito"],
        "description": ["concepto", "descripcion", "descripción", "detalle", "observaciones"],
        "counterparty": ["contraparte", "beneficiario", "ordenante"],
        "balance": ["saldo", "saldo disponible", "saldo actual"],
        "currency": ["divisa", "moneda", "currency"],
        "reference": ["referencia", "ref", "numero operacion", "número operación"]
      },
      "noisePatterns": [
        "saldo inicial", "saldo final", "saldo anterior", "saldo actual", 
        "subtotal", "total", "totales", "página", "page", "extracto", 
        "periodo", "desde", "hasta", "nº de cuenta", "iban", "titular", "oficina"
      ],
      "numberFormat": {
        "decimal": ",",
        "thousand": "."
      },
      "dateHints": ["dd/mm/yyyy", "dd-mm-yyyy"],
      "minScore": 3,
      "useCargoAbono": true
    },
    {
      "bankKey": "ING",
      "bankVersion": "2025.01.15",
      "headerAliases": {
        "date": ["fecha", "fecha movimiento", "fecha de movimiento", "f. movimiento", "f. operacion", "date"],
        "valueDate": ["fecha valor", "fecha de valor", "f. valor"],
        "amount": ["importe", "cantidad", "monto", "import", "euros", "amount"],
        "description": ["descripcion", "concepto", "detalle", "descripción", "movimiento", "description"],
        "counterparty": ["contraparte", "beneficiario", "ordenante", "entidad"],
        "balance": ["saldo", "saldo disponible", "saldo actual", "balance"],
        "currency": ["divisa", "moneda", "currency"],
        "reference": ["referencia", "ref", "reference"]
      },
      "noisePatterns": [
        "saldo inicial", "saldo final", "saldo anterior", "saldo actual", 
        "subtotal", "total", "totales", "página", "page", "extracto", 
        "periodo", "desde", "hasta", "nº de cuenta", "iban", "titular", "oficina"
      ],
      "numberFormat": {
        "decimal": ",",
        "thousand": "."
      },
      "dateHints": ["dd/mm/yyyy", "dd-mm-yyyy"],
      "minScore": 3,
      "useCargoAbono": false
    },
    {
      "bankKey": "Openbank",
      "bankVersion": "2025.01.15",
      "headerAliases": {
        "date": ["fecha", "fecha operacion", "fecha operación", "f. operacion", "f. operación", "fecha mov"],
        "valueDate": ["fecha valor", "fecha de valor", "f. valor"],
        "amount": ["importe", "cantidad", "monto", "euros", "amount"],
        "cargo": ["cargo", "cargos", "debito", "débito"],
        "abono": ["abono", "abonos", "credito", "crédito"],
        "description": ["concepto", "descripcion", "descripción", "detalle", "description"],
        "counterparty": ["contraparte", "beneficiario", "ordenante"],
        "balance": ["saldo", "saldo disponible", "saldo actual", "balance"],
        "currency": ["divisa", "moneda", "currency"],
        "reference": ["referencia", "ref", "reference"]
      },
      "noisePatterns": [
        "saldo inicial", "saldo final", "saldo anterior", "saldo actual", 
        "subtotal", "total", "totales", "página", "page", "extracto", 
        "periodo", "desde", "hasta", "nº de cuenta", "iban", "titular", "oficina"
      ],
      "numberFormat": {
        "decimal": ",",
        "thousand": "."
      },
      "dateHints": ["dd/mm/yyyy", "dd-mm-yyyy"],
      "minScore": 3,
      "useCargoAbono": true
    },
    {
      "bankKey": "CaixaBank",
      "bankVersion": "2025.01.15",
      "headerAliases": {
        "date": ["fecha", "fecha operacion", "fecha operación", "f. operacion", "f. operación", "fecha mov"],
        "valueDate": ["fecha valor", "fecha de valor", "f. valor"],
        "amount": ["importe", "cantidad", "monto", "euros"],
        "cargo": ["cargo", "cargos", "debito", "débito"],
        "abono": ["abono", "abonos", "credito", "crédito"],
        "description": ["concepto", "descripcion", "descripción", "detalle"],
        "counterparty": ["contraparte", "beneficiario", "ordenante"],
        "balance": ["saldo", "saldo disponible", "saldo actual"],
        "currency": ["divisa", "moneda", "currency"],
        "reference": ["referencia", "ref", "numero operacion", "número operación"]
      },
      "noisePatterns": [
        "saldo inicial", "saldo final", "saldo anterior", "saldo actual", 
        "subtotal", "total", "totales", "página", "page", "extracto", 
        "periodo", "desde", "hasta", "nº de cuenta", "iban", "titular", "oficina"
      ],
      "numberFormat": {
        "decimal": ",",
        "thousand": "."
      },
      "dateHints": ["dd/mm/yyyy", "dd-mm-yyyy"],
      "minScore": 3,
      "useCargoAbono": true
    },
    {
      "bankKey": "Revolut",
      "bankVersion": "2025.01.15",
      "headerAliases": {
        "date": ["fecha", "date", "fecha operacion", "completed date"],
        "valueDate": ["fecha valor", "value date", "f. valor"],
        "amount": ["importe", "amount", "cantidad", "monto", "euros", "eur"],
        "cargo": ["paid out", "cargo", "debito"],
        "abono": ["paid in", "abono", "credito"],
        "description": ["descripcion", "description", "concepto", "reference"],
        "counterparty": ["contraparte", "counterparty", "beneficiario"],
        "balance": ["saldo", "balance"],
        "currency": ["currency", "divisa", "moneda"],
        "reference": ["reference", "referencia", "ref"]
      },
      "noisePatterns": [
        "saldo inicial", "saldo final", "saldo anterior", "saldo actual", 
        "subtotal", "total", "totales", "página", "page", "extracto", 
        "periodo", "desde", "hasta", "nº de cuenta", "iban", "titular", "oficina"
      ],
      "numberFormat": {
        "decimal": ",",
        "thousand": "."
      },
      "dateHints": ["dd/mm/yyyy", "dd-mm-yyyy", "yyyy-mm-dd"],
      "minScore": 3,
      "useCargoAbono": true
    }
  ]
}